{
  "projeto_id": 50612,
  "tipo_alvara": 2,
  "url": "https://www10.goiania.go.gov.br/alvarafacil/AcompanhaAprovacaoProjeto.aspx?ProjetoId=50612&TipoAlvara=2",
  "situacao": "Apto para Análise",
  "numero_licenca": null,
  "tipo": "Aprovação de Projeto",
  "autor": "HUGO FERNANDES RIBAS JUNIOR ( 05099563198 )",
  "andamentos": [
    {
      "sequencia": "2",
      "data": "10/06/2026 09:08:04",
      "descricao": "Solicitação recebida",
      "situacao": "Em Execução",
      "responsavel": "CAMILA DA SILVA"
    },
    {
      "sequencia": "1",
      "data": "27/05/2026 07:37:35",
      "descricao": "Solicitação Aberta.",
      "situacao": "Aberta",
      "responsavel": "U B UTILIDADES LIMITADA"
    }
  ],
  "anexos": [],
  "_salvo_em": "2026-06-10T14:29:24.601651+00:00"
}